{
  "data_scores": [
    {
      "data_total": 2000
    }
  ],
  "champions": [
    {
      "name": "Brian R.",
      "score": 17400
    },
    {
      "name": "Ben C.",
      "score": 8750
    },
    {
      "name": "Ben C.",
      "score": 10250
    },
    {
      "name": "Ben C.",
      "score": 10900
    },
    {
      "name": "Ben C.",
      "score": 11750
    },
    {
      "name": "Brian R.",
      "score": 6250
    },
    {
      "name": "Ben C.",
      "score": 12000
    },
    {
      "name": "Ben C.",
      "score": 13700
    },
    {
      "name": "Brian R.",
      "score": 8850
    },
    {
      "name": "Brian R.",
      "score": 9000
    },
    {
      "name": "Kristina K.",
      "score": 11550
    },
    {
      "name": "Kristina K.",
      "score": 4350
    },
    {
      "name": "Kristina K.",
      "score": 8050
    },
    {
      "name": "Brian R.",
      "score": 12300
    },
    {
      "name": "Brian R.",
      "score": 15200
    },
    {
      "name": "Ben C.",
      "score": 11450
    },
    {
      "name": "Ben C.",
      "score": 15850
    },
    {
      "name": "Kristina K.",
      "score": 10450
    },
    {
      "name": "Ben C.",
      "score": 13418
    },
    {
      "name": "Ben C.",
      "score": 14240
    },
    {
      "name": "Ben C.",
      "score": 16022
    },
    {
      "name": "Ben C.",
      "score": 17698
    },
    {
      "name": "Ben C.",
      "score": 17358
    },
    {
      "name": "Kristina K.",
      "score": 15140
    },
    {
      "name": "Ben C.",
      "score": 18360
    },
    {
      "name": "Ben C.",
      "score": 17332
    },
    {
      "name": "Ben C.",
      "score": 19200
    },
    {
      "name": "Ben C.",
      "score": 18874
    },
    {
      "name": "Ben C.",
      "score": 18278
    },
    {
      "name": "Ben C.",
      "score": 18822
    }
  ],
  "parameters": [
    {
      "enemy_speed": 6000
    }
  ]
}